topsis_py/topsis.py
TOPSIS_Priyanshu_101803308-0.0.1.dist-info/LICENSE
TOPSIS_Priyanshu_101803308-0.0.1.dist-info/METADATA
TOPSIS_Priyanshu_101803308-0.0.1.dist-info/WHEEL
TOPSIS_Priyanshu_101803308-0.0.1.dist-info/entry_points.txt
TOPSIS_Priyanshu_101803308-0.0.1.dist-info/top_level.txt
TOPSIS_Priyanshu_101803308-0.0.1.dist-info/RECORD
