Metadata-Version: 2.1
Name: TOPSIS-Priyanshu-101803308
Version: 0.0.1
Summary: A Python package implementing TOPSIS technique.
Home-page: UNKNOWN
Author: Priyanshu Aggarwal
Author-email: priyanshua098@gmail.com
License: MIT
Keywords: Ranking,Topsis
Platform: UNKNOWN
Classifier: License :: OSI Approved :: MIT License
Classifier: Programming Language :: Python :: 3.7
Requires-Dist: scipy
Requires-Dist: numpy
Requires-Dist: pandas
